LICENSE
MANIFEST.in
README.md
pyproject.toml
setup.py
carl/__init__.py
carl/py.typed
carl/context/__init__.py
carl/context/context_space.py
carl/context/sampler.py
carl/context/search_space_encoding.py
carl/context/selection.py
carl/context/utils.py
carl/envs/__init__.py
carl/envs/carl_env.py
carl/envs/brax/__init__.py
carl/envs/brax/carl_ant.py
carl/envs/brax/carl_brax_env.py
carl/envs/brax/carl_halfcheetah.py
carl/envs/brax/carl_hopper.py
carl/envs/brax/carl_humanoid.py
carl/envs/brax/carl_humanoidstandup.py
carl/envs/brax/carl_inverted_double_pendulum.py
carl/envs/brax/carl_inverted_pendulum.py
carl/envs/brax/carl_pusher.py
carl/envs/brax/carl_reacher.py
carl/envs/brax/carl_walker2d.py
carl/envs/brax/wrappers.py
carl/envs/dmc/__init__.py
carl/envs/dmc/carl_dm_finger.py
carl/envs/dmc/carl_dm_fish.py
carl/envs/dmc/carl_dm_quadruped.py
carl/envs/dmc/carl_dm_walker.py
carl/envs/dmc/carl_dmcontrol.py
carl/envs/dmc/loader.py
carl/envs/dmc/wrappers.py
carl/envs/dmc/dmc_tasks/__init__.py
carl/envs/dmc/dmc_tasks/finger.py
carl/envs/dmc/dmc_tasks/fish.py
carl/envs/dmc/dmc_tasks/quadruped.py
carl/envs/dmc/dmc_tasks/utils.py
carl/envs/dmc/dmc_tasks/walker.py
carl/envs/gymnasium/__init__.py
carl/envs/gymnasium/carl_gymnasium_env.py
carl/envs/gymnasium/box2d/__init__.py
carl/envs/gymnasium/box2d/carl_bipedal_walker.py
carl/envs/gymnasium/box2d/carl_lunarlander.py
carl/envs/gymnasium/box2d/carl_vehicle_racing.py
carl/envs/gymnasium/box2d/parking_garage/__init__.py
carl/envs/gymnasium/box2d/parking_garage/bus.py
carl/envs/gymnasium/box2d/parking_garage/race_car.py
carl/envs/gymnasium/box2d/parking_garage/street_car.py
carl/envs/gymnasium/box2d/parking_garage/trike.py
carl/envs/gymnasium/box2d/parking_garage/utils.py
carl/envs/gymnasium/classic_control/__init__.py
carl/envs/gymnasium/classic_control/carl_acrobot.py
carl/envs/gymnasium/classic_control/carl_cartpole.py
carl/envs/gymnasium/classic_control/carl_mountaincar.py
carl_gym.egg-info/PKG-INFO
carl_gym.egg-info/SOURCES.txt
carl_gym.egg-info/dependency_links.txt
carl_gym.egg-info/requires.txt
carl_gym.egg-info/top_level.txt