Metadata-Version: 2.1
Name: carl-gym
Version: 1.0.0
Summary: CARL- Contextually Adaptive Reinforcement Learning
Home-page: https://www.automl.org/
Author: Carolin Benjamins, Theresa Eimer, Frederik Schubert, André Biedenkapp, Aditya Mohan, Sebastian Döhler
Author-email: benjamins@tnt.uni-hannover.de
License: Apache 2.0
Project-URL: Documentation, https://automl.github.io/CARL
Project-URL: Source Code, https://github.com/https://github.com/automl/CARL
Keywords: RL,Generalization,Context,Reinforcement Learning
Platform: Linux
Classifier: Programming Language :: Python :: 3
Classifier: Natural Language :: English
Classifier: Environment :: Console
Classifier: Intended Audience :: Developers
Classifier: Intended Audience :: Education
Classifier: Intended Audience :: Science/Research
Classifier: License :: OSI Approved :: Apache Software License
Classifier: Operating System :: POSIX :: Linux
Classifier: Topic :: Scientific/Engineering :: Artificial Intelligence
Classifier: Topic :: Scientific/Engineering
Classifier: Topic :: Software Development
Requires-Python: >=3.9
Provides-Extra: box2d
Provides-Extra: brax
Provides-Extra: dm_control
Provides-Extra: mario
Provides-Extra: dev
Provides-Extra: docs
License-File: LICENSE
